stqe/__about__.py
stqe/__init__.py
stqe/stqe_test.py
stqe/stqe_tool.py
stqe/conf/__init__.py
stqe/conf/lvm/__init__.py
stqe/conf/lvm/lvm-thinp-basic.conf
stqe/host/__init__.py
stqe/host/atomic_run.py
stqe/host/beaker.py
stqe/host/fmf_tools.py
stqe/host/iscsi.py
stqe/host/logchecker.py
stqe/host/lsm.py
stqe/host/lvm.py
stqe/host/nfs_lock.py
stqe/host/persistent_vars.py
stqe/host/restraint.py
stqe/host/stratis.py
stqe/host/tc.py
stqe/host/vdo.py
stqe/tests/__init__.py
stqe/tests/.fmf/version
stqe/tests/dm/__init__.py
stqe/tests/dm/block_boundary_obedience.py
stqe/tests/dm/error_block_alignment.py
stqe/tests/dm/main.fmf
stqe/tests/hba/__init__.py
stqe/tests/hba/add_new_lun.py
stqe/tests/hba/dev_loss_tmo.py
stqe/tests/hba/io-failover-alternate-interface.py
stqe/tests/hba/io-remove-lun.py
stqe/tests/hba/mp_failover.py
stqe/tests/hba/online_offline.py
stqe/tests/hba/oscilate_port.py
stqe/tests/hba/show_driver_info.py
stqe/tests/iscsi/__init__.py
stqe/tests/iscsi/iscsi_params.py
stqe/tests/iscsi/main.fmf
stqe/tests/iscsi/cli/__init__.py
stqe/tests/iscsi/cli/iscsi_local_target.py
stqe/tests/iscsi/cli/main.fmf
stqe/tests/iscsi/setup/__init__.py
stqe/tests/iscsi/setup/create_backstore.py
stqe/tests/iscsi/setup/create_fileio_target.py
stqe/tests/iscsi/setup/delete_backstore.py
stqe/tests/iscsi/setup/delete_iscsi_target.py
stqe/tests/iscsi/setup/main.fmf
stqe/tests/iscsi/setup/start_multipath.py
stqe/tests/iscsi/setup/stop_multipath.py
stqe/tests/lsm/__init__.py
stqe/tests/lsm/main.fmf
stqe/tests/lsm/lsmcli/__init__.py
stqe/tests/lsm/lsmcli/main.fmf
stqe/tests/lsm/lsmcli/access_group/__init__.py
stqe/tests/lsm/lsmcli/access_group/access_group_add.py
stqe/tests/lsm/lsmcli/access_group/access_group_create.py
stqe/tests/lsm/lsmcli/access_group/access_group_delete.py
stqe/tests/lsm/lsmcli/access_group/access_group_remove.py
stqe/tests/lsm/lsmcli/access_group/access_group_volumes.py
stqe/tests/lsm/lsmcli/access_group/main.fmf
stqe/tests/lsm/lsmcli/fs/__init__.py
stqe-0.2.7.dist-info/METADATA
stqe-0.2.7.dist-info/WHEEL
stqe-0.2.7.dist-info/entry_points.txt
stqe-0.2.7.dist-info/licenses/LICENSE
stqe-0.2.7.dist-info/RECORD
